{
    "sucesso": true,
    "paginas": 2,
    "resultados": [
        {
            "id": 0,
            "nome": "Resposta"
           
        },
        {
            "id": 1,
         "nome": "Resposta"
        },
        {
            "id": 2,
         "nome": "Resposta"
        },
        {
            "id": 3,
         "nome": "Resposta"
        },
        {
            "id": 4,
         "nome": "Resposta"
        },
        {
            "id": 5,
         "nome": "Resposta"
        },
        {
            "id": 6,
         "nome": "Resposta"
        },
        {
            "id": 7,
         "nome": "Resposta"
        },
        {
            "id": 8,
         "nome": "Resposta"
        },
        {
            "id": 9,
         "nome": "Resposta"
        },
        {
            "id": 10,
         "nome": "Resposta"
        },
        {
            "id": 11,
         "nome": "Resposta"
        },
        {
            "id": 12,
         "nome": "Resposta"
        },
        {
            "id": 13,
         "nome": "Resposta"
        },
        {
            "id": 14,
         "nome": "Resposta"
        },
        {
            "id": 15,
         "nome": "Resposta"
        },
        {
            "id": 16,
         "nome": "Resposta"
        },
        {
            "id": 17,
         "nome": "Resposta"
        },
        {
            "id": 18,
         "nome": "Resposta"
        },
        {
            "id": 19,
         "nome": "Resposta"
        }
    ]
}